jk_simpleexec/CommandResult.py
jk_simpleexec/TextDataProcessingPolicy.py
jk_simpleexec/WhereIs.py
jk_simpleexec/_DebugValveToFile.py
jk_simpleexec/__init__.py
jk_simpleexec/_common.py
jk_simpleexec/invoke_utils.py
jk_simpleexec/simpleexec.py
jk_simpleexec-0.2024.8.11.dist-info/WHEEL
jk_simpleexec-0.2024.8.11.dist-info/METADATA
jk_simpleexec-0.2024.8.11.dist-info/RECORD
