Metadata-Version: 2.1
Name: jk_simpleexec
Version: 0.2024.8.11
Summary: Python module to run command line programs in a convenient way and retrieve their output after they terminated.
Keywords: exec,shell,execute,Popen,kill,spawn
Author-email: Jürgen Knauth <pubsrc@binary-overflow.de>
Maintainer-email: Jürgen Knauth <pubsrc@binary-overflow.de>
Requires-Python: >=3.8
Classifier: Development Status :: 3 - Alpha
Classifier: Programming Language :: Python :: 3
Classifier: License :: OSI Approved :: Apache Software License
Requires-Dist: invoke
Requires-Dist: jk_prettyprintobj
Requires-Dist: jk_cmdoutputparsinghelper
